blage.cp310-win_amd64.pyd
blage-1.0.0.dist-info/licenses/LICENSE
blage-1.0.0.dist-info/METADATA
blage-1.0.0.dist-info/WHEEL
blage-1.0.0.dist-info/top_level.txt
blage-1.0.0.dist-info/RECORD
