Metadata-Version: 2.4
Name: blage
Version: 1.0.0
Summary: A Python library for block-based image processing
Home-page: https://github.com/XENOXI/blockImage
Author: Vasiliy Lekomtsev
Author-email: Vasiliy Lekomtsev <mexerily@gmail.com>
License-Expression: MIT
Project-URL: Homepage, https://github.com/XENOXI/blockImage
Classifier: Programming Language :: Python :: 3
Classifier: Operating System :: OS Independent
Requires-Python: >=3.7
License-File: LICENSE
Dynamic: author
Dynamic: home-page
Dynamic: license-file
